setup.py
HowLong/HowLong.py
HowLong/__init__.py
howlong.egg-info/PKG-INFO
howlong.egg-info/SOURCES.txt
howlong.egg-info/dependency_links.txt
howlong.egg-info/entry_points.txt
howlong.egg-info/top_level.txt