Metadata-Version: 1.0
Name: howlong
Version: 0.0.2
Summary: A simple timing utility for long running processes
Home-page: https://github.com/mattjegan/howlong
Author: Matthew Egan
Author-email: matthewj.egan@hotmai.com
License: UNKNOWN
Platform: UNKNOWN
